kcloader/tools.py
kcloader/resource/__init__.py
kcloader/resource/base_manager.py
kcloader/resource/client_resource.py
kcloader/resource/client_scope_resource.py
kcloader/resource/custom_authentication_resource.py
kcloader/resource/default_client_scope_resource.py
kcloader/resource/group_resource.py
kcloader/resource/identity_provider_resource.py
kcloader/resource/many_resources.py
kcloader/resource/protocol_mapper.py
kcloader/resource/realm_resource.py
kcloader/resource/realm_role_resource.py
kcloader/resource/resource.py
kcloader/resource/resource_publisher.py
kcloader/resource/role_resource.py
kcloader/resource/scope_mappings.py
kcloader/resource/single_resource.py
kcloader/resource/user_federation_resource.py
keycloak_exporter_bot-0.0.12.dist-info/METADATA
keycloak_exporter_bot-0.0.12.dist-info/WHEEL
keycloak_exporter_bot-0.0.12.dist-info/top_level.txt
keycloak_exporter_bot-0.0.12.dist-info/RECORD
