Metadata-Version: 2.1
Name: keycloak-exporter-bot
Version: 0.0.12
Summary: Import data into KeyCloak server
Author: Cesar Valdez
Project-URL: repository, https://github.com/justinc1/keycloak-exporter-bot
Keywords: KeyCloak
Requires-Python: >=3.8
Requires-Dist: kcapi (>=1.0.40)
Requires-Dist: keycloak-fetch-bot (==0.0.9)
Requires-Dist: sortedcontainers (>=2.4.0)
Provides-Extra: devel
